tests/__init__.py
tests/test_vitalfilepy.py
vitalfilepy/__init__.py
vitalfilepy/constant.py
vitalfilepy/vitalfile.py
vitalfilepy-0.0.1.dist-info/LICENSE
vitalfilepy-0.0.1.dist-info/METADATA
vitalfilepy-0.0.1.dist-info/WHEEL
vitalfilepy-0.0.1.dist-info/top_level.txt
vitalfilepy-0.0.1.dist-info/RECORD
