Metadata-Version: 2.1
Name: vitalfilepy
Version: 0.0.1
Summary: Software library to read and write binary file for vital sign (.vital format)
Home-page: https://github.com/hulab-ucsf/vitalfilepy.git
Author: Peter Li@HuLab UCSF
Author-email: peter0306@gmail.com
License: UNKNOWN
Keywords: vital sign vitalsign binary
Platform: UNKNOWN
Classifier: Programming Language :: Python :: 3
Classifier: License :: OSI Approved :: MIT License
Classifier: Operating System :: OS Independent
Requires-Python: >=2.7, !=3.0.*, !=3.1.*, !=3.2.*, !=3.3.*, <4
